{
  "deploy": "created",
  "regime": "FRAGILE",
  "score": 63.5,
  "balance_sheet": "FLAT",
  "qt_not_qe": true,
  "drivers": [
    "Reserves $3.01T vs ~$3.0T floor \u2014 approaching LCLoR",
    "ON-RRP $1B \u2014 EMPTY: shock absorber gone, every drain now hits reserves directly",
    "Fed balance sheet FLAT (+0B over 8wk) \u2014 QT may have ended, but this is NOT QE. No new liquidity is being added; with RRP empty, issuance still drains reserves.",
    "SOFR\u2212IORB -3bps \u2014 calm"
  ],
  "signals": {
    "balance_sheet": "Fed balance sheet FLAT (+0B over 8wk) \u2014 QT may have ended, but this is NOT QE. No new liquidity is being added; with RRP empty, issuance still drains reserves.",
    "reserves": "Reserves $3.01T vs ~$3.0T floor \u2014 approaching LCLoR",
    "rrp_cushion": "ON-RRP $1B \u2014 EMPTY: shock absorber gone, every drain now hits reserves directly",
    "sofr_iorb": "SOFR\u2212IORB -3bps \u2014 calm",
    "sofr_effr": "SOFR\u2212EFFR +0bps (normal)",
    "tga": "TGA falling ($-2048B/4wk) \u2014 releasing cash into reserves (supportive)"
  }
}