{
  "started": "2026-05-08T15:39:44.445271+00:00",
  "test": {
    "results": [
      {
        "url": "https://justhodl.ai/chart-pro.html",
        "status": 200,
        "bytes": 143855,
        "headers": {
          "server": "GitHub.com",
          "last-modified": "Fri, 08 May 2026 15:32:58 GMT",
          "etag": "\"69fe022a-23db9\"",
          "cache-control": "max-age=600",
          "x-github-request-id": "B0C2:33C734:FC6107:1118355:69FE03C6",
          "age": "0",
          "x-served-by": "cache-iad-kiad7000175-IAD"
        },
        "v9_markers_found": [
          "v9",
          "VWAP",
          "Ichimoku",
          "ATR (14)",
          "ADX (14)",
          "Fibonacci",
          "aiPane",
          "replayBar",
          "cmdOverlay",
          "regimeBanner",
          "Chart Pro v9"
        ],
        "v9_markers_missing": [],
        "v9_score": "11/11",
        "is_v9": true,
        "title": "Chart Pro \u00b7 JustHodl.AI \u00b7 v9"
      },
      {
        "url": "https://www.justhodl.ai/chart-pro.html",
        "status": 200,
        "bytes": 143855,
        "headers": {
          "server": "GitHub.com",
          "last-modified": "Fri, 08 May 2026 15:32:58 GMT",
          "etag": "\"69fe022a-23db9\"",
          "cache-control": "max-age=600",
          "x-github-request-id": "B0C2:33C734:FC6107:1118355:69FE03C6",
          "age": "0",
          "x-served-by": "cache-iad-kjyo7100154-IAD"
        },
        "v9_markers_found": [
          "v9",
          "VWAP",
          "Ichimoku",
          "ATR (14)",
          "ADX (14)",
          "Fibonacci",
          "aiPane",
          "replayBar",
          "cmdOverlay",
          "regimeBanner",
          "Chart Pro v9"
        ],
        "v9_markers_missing": [],
        "v9_score": "11/11",
        "is_v9": true,
        "title": "Chart Pro \u00b7 JustHodl.AI \u00b7 v9"
      },
      {
        "url": "https://elmooro.github.io/si/chart-pro.html",
        "status": 200,
        "bytes": 143855,
        "headers": {
          "server": "GitHub.com",
          "last-modified": "Fri, 08 May 2026 15:32:58 GMT",
          "etag": "\"69fe022a-23db9\"",
          "cache-control": "max-age=600",
          "x-github-request-id": "B0C2:33C734:FC6107:1118355:69FE03C6",
          "age": "0",
          "x-served-by": "cache-iad-kiad7000062-IAD"
        },
        "v9_markers_found": [
          "v9",
          "VWAP",
          "Ichimoku",
          "ATR (14)",
          "ADX (14)",
          "Fibonacci",
          "aiPane",
          "replayBar",
          "cmdOverlay",
          "regimeBanner",
          "Chart Pro v9"
        ],
        "v9_markers_missing": [],
        "v9_score": "11/11",
        "is_v9": true,
        "title": "Chart Pro \u00b7 JustHodl.AI \u00b7 v9"
      }
    ]
  },
  "finished": "2026-05-08T15:39:51.520633+00:00"
}