{
  "started": "2026-05-13T09:39:31.595753+00:00",
  "env_keys": [
    "POLY_KEY",
    "TELEGRAM_CHAT_ID",
    "TELEGRAM_TOKEN"
  ],
  "deploy": "created",
  "schedule": "ok",
  "invoke_status": 200,
  "fn_error": null,
  "invoke_response": {
    "success": true,
    "version": "1.0.0",
    "n_underlyings": 0,
    "spy_regime": null,
    "spy_gex_b": null,
    "spy_flip": null,
    "composite_regime": null,
    "n_squeeze_candidates": 0,
    "alert_sent": false,
    "elapsed_seconds": 0.35
  },
  "log_tail": "START RequestId: dfd029d2-2d70-4a19-9da8-b858efea20ff Version: $LATEST\n=== DEALER-GEX v1.0.0 \u00b7 2026-05-13T09:39:40.881959+00:00 ===\nanalyzing SPY...\nanalyzing QQQ...\nanalyzing IWM...\nanalyzing NVDA...\nchain SPY page 0 err: HTTP Error 403: Forbidden\nanalyzing TSLA...\nchain IWM page 0 err: HTTP Error 403: Forbidden\nanalyzing AAPL...\nchain QQQ page 0 err: HTTP Error 403: Forbidden\nanalyzing META...\nchain NVDA page 0 err: HTTP Error 403: Forbidden\nanalyzing AMZN...\nchain TSLA page 0 err: HTTP Error 403: Forbidden\nanalyzing MSFT...\nchain AAPL page 0 err: HTTP Error 403: Forbidden\nanalyzing GOOGL...\nchain AMZN page 0 err: HTTP Error 403: Forbidden\nchain META page 0 err: HTTP Error 403: Forbidden\nchain MSFT page 0 err: HTTP Error 403: Forbidden\nchain GOOGL page 0 err: HTTP Error 403: Forbidden\n\u2713 dealer-gex.json written (1.0 KB)\nEND RequestId: dfd029d2-2d70-4a19-9da8-b858efea20ff\nREPORT RequestId: dfd029d2-2d70-4a19-9da8-b858efea20ff\tDuration: 354.96 ms\tBilled Duration: 894 ms\tMemory Size: 2048 MB\tMax Memory Used: 107 MB\tInit Duration: 538.83 ms\t\n",
  "sidecar": {
    "size_kb": 0.9,
    "modified": "2026-05-13T09:39:42",
    "version": "1.0.0",
    "market_composite": {},
    "squeeze_candidates_count": 0,
    "squeeze_top_3": [],
    "underlyings": {
      "SPY": {
        "spot": 738.18,
        "total_gex_b": null,
        "flip": null,
        "pct_to_flip": null,
        "regime": null,
        "pcr_oi": null,
        "pcr_vol": null,
        "n_contracts": null,
        "max_pain": [],
        "zero_dte_pct": null,
        "skew": null,
        "err": "no options chain"
      },
      "IWM": {
        "spot": 282.57,
        "total_gex_b": null,
        "flip": null,
        "pct_to_flip": null,
        "regime": null,
        "pcr_oi": null,
        "pcr_vol": null,
        "n_contracts": null,
        "max_pain": [],
        "zero_dte_pct": null,
        "skew": null,
        "err": "no options chain"
      },
      "QQQ": {
        "spot": 707.24,
        "total_gex_b": null,
        "flip": null,
        "pct_to_flip": null,
        "regime": null,
        "pcr_oi": null,
        "pcr_vol": null,
        "n_contracts": null,
        "max_pain": [],
        "zero_dte_pct": null,
        "skew": null,
        "err": "no options chain"
      },
      "NVDA": {
        "spot": 220.78,
        "total_gex_b": null,
        "flip": null,
        "pct_to_flip": null,
        "regime": null,
        "pcr_oi": null,
        "pcr_vol": null,
        "n_contracts": null,
        "max_pain": [],
        "zero_dte_pct": null,
        "skew": null,
        "err": "no options chain"
      },
      "TSLA": {
        "spot": 433.45,
        "total_gex_b": null,
        "flip": null,
        "pct_to_flip": null,
        "regime": null,
        "pcr_oi": null,
        "pcr_vol": null,
        "n_contracts": null,
        "max_pain": [],
        "zero_dte_pct": null,
        "skew": null,
        "err": "no options chain"
      },
      "AAPL": {
        "spot": 294.8,
        "total_gex_b": null,
        "flip": null,
        "pct_to_flip": null,
        "regime": null,
        "pcr_oi": null,
        "pcr_vol": null,
        "n_contracts": null,
        "max_pain": [],
        "zero_dte_pct": null,
        "skew": null,
        "err": "no options chain"
      },
      "AMZN": {
        "spot": 265.82,
        "total_gex_b": null,
        "flip": null,
        "pct_to_flip": null,
        "regime": null,
        "pcr_oi": null,
        "pcr_vol": null,
        "n_contracts": null,
        "max_pain": [],
        "zero_dte_pct": null,
        "skew": null,
        "err": "no options chain"
      },
      "META": {
        "spot": 603.0,
        "total_gex_b": null,
        "flip": null,
        "pct_to_flip": null,
        "regime": null,
        "pcr_oi": null,
        "pcr_vol": null,
        "n_contracts": null,
        "max_pain": [],
        "zero_dte_pct": null,
        "skew": null,
        "err": "no options chain"
      },
      "MSFT": {
        "spot": 407.77,
        "total_gex_b": null,
        "flip": null,
        "pct_to_flip": null,
        "regime": null,
        "pcr_oi": null,
        "pcr_vol": null,
        "n_contracts": null,
        "max_pain": [],
        "zero_dte_pct": null,
        "skew": null,
        "err": "no options chain"
      },
      "GOOGL": {
        "spot": 387.35,
        "total_gex_b": null,
        "flip": null,
        "pct_to_flip": null,
        "regime": null,
        "pcr_oi": null,
        "pcr_vol": null,
        "n_contracts": null,
        "max_pain": [],
        "zero_dte_pct": null,
        "skew": null,
        "err": "no options chain"
      }
    }
  },
  "finished": "2026-05-13T09:39:41.589071+00:00"
}